AlibabaXinJijianDongchaZhi5gZhinengJingjiYingyongChangjingFix1/README.md
AlibabaXinJijianDongchaZhi5gZhinengJingjiYingyongChangjingFix1/__init__.py
AlibabaXinJijianDongchaZhi5gZhinengJingjiYingyongChangjingFix1/__main__.py
AlibabaXinJijianDongchaZhi5gZhinengJingjiYingyongChangjingFix1/file.pdf
AlibabaXinJijianDongchaZhi5gZhinengJingjiYingyongChangjingFix1/index.html
alibaba_xin_jijian_dongcha_zhi_5g_zhineng_jingji_yingyong_changjing_fix1-2025.3.25.0.dist-info/METADATA
alibaba_xin_jijian_dongcha_zhi_5g_zhineng_jingji_yingyong_changjing_fix1-2025.3.25.0.dist-info/WHEEL
alibaba_xin_jijian_dongcha_zhi_5g_zhineng_jingji_yingyong_changjing_fix1-2025.3.25.0.dist-info/entry_points.txt
alibaba_xin_jijian_dongcha_zhi_5g_zhineng_jingji_yingyong_changjing_fix1-2025.3.25.0.dist-info/top_level.txt
alibaba_xin_jijian_dongcha_zhi_5g_zhineng_jingji_yingyong_changjing_fix1-2025.3.25.0.dist-info/RECORD
